{"updated": "2026-05-17T21:53:23Z", "rows": [{"t": "2026-05-18T00:00", "wave": 0.86, "wind": 2.7, "dir": 243, "waveDir": 110, "windWave": 0.0, "rain": 0.0}, {"t": "2026-05-18T06:00", "wave": 0.82, "wind": 2.6, "dir": 54, "waveDir": 110, "windWave": 0.0, "rain": 0.0}, {"t": "2026-05-18T12:00", "wave": 0.84, "wind": 5.6, "dir": 79, "waveDir": 108, "windWave": 0.04, "rain": 0.0}, {"t": "2026-05-18T18:00", "wave": 0.9, "wind": 3.8, "dir": 147, "waveDir": 108, "windWave": 0.1, "rain": 0.0}, {"t": "2026-05-19T00:00", "wave": 0.9, "wind": 3.3, "dir": 121, "waveDir": 108, "windWave": 0.08, "rain": 0.0}, {"t": "2026-05-19T06:00", "wave": 0.9, "wind": 3.5, "dir": 125, "waveDir": 113, "windWave": 0.0, "rain": 0.0}, {"t": "2026-05-19T12:00", "wave": 1.06, "wind": 4.3, "dir": 106, "waveDir": 126, "windWave": 0.32, "rain": 0.0}, {"t": "2026-05-19T18:00", "wave": 1.16, "wind": 3.5, "dir": 112, "waveDir": 133, "windWave": 0.22, "rain": 0.2}, {"t": "2026-05-20T00:00", "wave": 1.4, "wind": 5.8, "dir": 80, "waveDir": 137, "windWave": 0.76, "rain": 2.6}, {"t": "2026-05-20T06:00", "wave": 1.9, "wind": 5.6, "dir": 44, "waveDir": 159, "windWave": 0.96, "rain": 4.7}, {"t": "2026-05-20T12:00", "wave": 1.76, "wind": 6.8, "dir": 183, "waveDir": 164, "windWave": 0.48, "rain": 0.5}, {"t": "2026-05-20T18:00", "wave": 1.7, "wind": 9.3, "dir": 37, "waveDir": 170, "windWave": 0.52, "rain": 1.7}, {"t": "2026-05-21T00:00", "wave": 1.8, "wind": 6.3, "dir": 31, "waveDir": 176, "windWave": 1.04, "rain": 0.1}, {"t": "2026-05-21T06:00", "wave": 2.06, "wind": 9.2, "dir": 244, "waveDir": 189, "windWave": 1.22, "rain": 0.3}, {"t": "2026-05-21T12:00", "wave": 2.4, "wind": 8.3, "dir": 227, "waveDir": 199, "windWave": 2.1, "rain": 2.5}, {"t": "2026-05-21T18:00", "wave": 2.72, "wind": 8.2, "dir": 254, "waveDir": 211, "windWave": 2.34, "rain": 0.2}, {"t": "2026-05-22T00:00", "wave": 2.12, "wind": 9.7, "dir": 39, "waveDir": 207, "windWave": 0.62, "rain": 0.4}, {"t": "2026-05-22T06:00", "wave": 1.58, "wind": 8.2, "dir": 38, "waveDir": 195, "windWave": 0.08, "rain": 0.0}, {"t": "2026-05-22T12:00", "wave": 1.5, "wind": 10.7, "dir": 57, "waveDir": 153, "windWave": 0.58, "rain": 0.0}, {"t": "2026-05-22T18:00", "wave": 1.32, "wind": 7.8, "dir": 83, "waveDir": 119, "windWave": 0.82, "rain": 0.1}]}